odoo/addons/project_task_type_active/README.rst
odoo/addons/project_task_type_active/__init__.py
odoo/addons/project_task_type_active/__manifest__.py
odoo/addons/project_task_type_active/i18n/de.po
odoo/addons/project_task_type_active/i18n/project_task_type_active.pot
odoo/addons/project_task_type_active/models/__init__.py
odoo/addons/project_task_type_active/models/project_task_type.py
odoo/addons/project_task_type_active/readme/CONTRIBUTORS.rst
odoo/addons/project_task_type_active/readme/DESCRIPTION.rst
odoo/addons/project_task_type_active/static/description/icon.png
odoo/addons/project_task_type_active/static/description/index.html
odoo11_addon_project_task_type_active-11.0.1.0.0.99.dev8.dist-info/METADATA
odoo11_addon_project_task_type_active-11.0.1.0.0.99.dev8.dist-info/WHEEL
odoo11_addon_project_task_type_active-11.0.1.0.0.99.dev8.dist-info/top_level.txt
odoo11_addon_project_task_type_active-11.0.1.0.0.99.dev8.dist-info/RECORD
